aixiv/__init__.py
aixiv-0.0.1.dist-info/LICENSE
aixiv-0.0.1.dist-info/METADATA
aixiv-0.0.1.dist-info/WHEEL
aixiv-0.0.1.dist-info/RECORD
