Metadata-Version: 2.1
Name: aixiv
Version: 0.0.1
Summary: Translation and summarization of arXiv by generative AI
Home-page: https://github.com/astropenguin/aixiv/
License: MIT
Keywords: arxiv,translation,summarization,generative-ai
Author: Akio Taniguchi
Author-email: taniguchi@a.phys.nagoya-u.ac.jp
Requires-Python: >=3.9,<3.13
Classifier: License :: OSI Approved :: MIT License
Classifier: Programming Language :: Python :: 3
Classifier: Programming Language :: Python :: 3.9
Classifier: Programming Language :: Python :: 3.10
Classifier: Programming Language :: Python :: 3.11
Classifier: Programming Language :: Python :: 3.12
Requires-Dist: typing-extensions (>=4.1,<5.0)
Project-URL: Documentation, https://astropenguin.github.io/aixiv/
